{
    "filterBar.showAll": {
        "value": "Show all",
        "comment": "",
        "limit": 0
    },
    "filterBar.showLess": {
        "value": "Show less",
        "comment": "",
        "limit": 0
    },
    "options.menu.export.PDF": {
        "value": "Export to PDF",
        "comment": "Export whole KPI dashboard to PDF",
        "limit": 0
    },
    "options.menu.export.PDF.error": {
        "value": "Export to PDF failed. Please try again.",
        "comment": "Export whole KPI dashboard to PDF failed",
        "limit": 0
    },
    "options.menu.schedule.email": {
        "value": "Schedule emailing",
        "comment": "Translate as imperative. Schedule emailing whole KPI dashboard",
        "limit": 0
    },
    "dialogs.schedule.email.submit.success": {
        "value": "Success! Your dashboard is scheduled for emailing.",
        "comment": "",
        "limit": 0
    },
    "dialogs.schedule.email.submit.error": {
        "value": "Failed to schedule the dashboard. Try again later.",
        "comment": "",
        "limit": 0
    },
    "drill_modal_picker.drill-down": {
        "value": "Drill down",
        "comment": "Title of widget interactions",
        "limit": 0
    },
    "drill_modal_picker.drill-into": {
        "value": "Drill into",
        "comment": "Title of widget interactions",
        "limit": 0
    },
    "drill_modal_picker.more.details": {
        "value": "More details",
        "comment": "",
        "limit": 0
    },
    "drillModal.backToTop": {
        "value": "Back to top",
        "comment": "",
        "limit": 0
    }
}
