{
    "empty_value": "pusta wartość",
    "gs.date.at": "w",
    "gs.header.help": "Pomoc",
    "gs.header.logout": "Wyloguj się",
    "gs.list.all": "Wszystko",
    "gs.list.except": "z wyjątkiem",
    "gs.list.is": "jest",
    "gs.list.search.placeholder": "Szukaj…",
    "gs.list.notAvailableAbbreviation": "N/D",
    "gs.list.searchResults": "wyniki wyszukiwania",
    "gs.visualizationsList.loading": "Ładowanie…",
    "gs.color-picker.inputPlaceholder": "#kolor",
    "gs.color-picker.currentColor": "bieżący",
    "gs.color-picker.newColor": "nowy",
    "gs.color-picker.cancelButton": "Anuluj",
    "gs.color-picker.okButton": "OK",
    "gs.color-picker.hex": "sześciokąt",
    "gs.noData.noMatchingData": "Brak pasujących danych",
    "gs.noData.noDataAvailable": "Brak pasujących danych",
    "geochart.scroll.zoom.blocker": "Użyj {button} + przewijanie, aby powiększyć mapę",
    "geochart.touch.pan.blocker": "Użyj dwóch palców, aby przesunąć mapę",
    "visualizations.of": "{page} z {pagesCount}",
    "visualizations.totals.dropdown.title.sum": "Suma",
    "visualizations.totals.dropdown.title.avg": "Średnia",
    "visualizations.totals.dropdown.title.min": "Min",
    "visualizations.totals.dropdown.title.max": "Maks",
    "visualizations.totals.dropdown.title.nat": "Podsumowanie (Suma)",
    "visualizations.totals.dropdown.tooltip.nat.disabled.ranking": "Agregacja podsumowania (Suma) nie jest dostępna podczas filtrowania wizualizacji za pomocą filtra rankingowego. Aby użyć podsumowania (Suma), usuń filtr rankingowy z paska filtrów.",
    "visualizations.totals.dropdown.title.med": "Mediana",
    "visualizations.headline.tertiary.title": "Versus",
    "visualizations.headline.comparison.title.change": "Zmień",
    "visualizations.headline.comparison.title.change.positive": "Zwiększ",
    "visualizations.headline.comparison.title.change.negative": "Zmniejsz",
    "visualizations.headline.comparison.title.change.equals": "Bez zmian",
    "visualizations.headline.comparison.title.ratio": "z",
    "visualizations.headline.comparison.title.difference": "Różnica",
    "visualizations.headline.comparison.title.difference.positive": "Zwiększ",
    "visualizations.headline.comparison.title.difference.negative": "Zmniejsz",
    "visualizations.headline.comparison.title.difference.equals": "Brak różnicy",
    "visualization.numericValues.k": "k",
    "visualization.numericValues.m": "M",
    "visualization.numericValues.g": "G",
    "visualization.numericValues.t": "T",
    "visualization.numericValues.p": "P",
    "visualization.numericValues.e": "E",
    "visualization.emptyValue": "pusta wartość",
    "visualization.waterfall.total": "Suma",
    "visualization.ErrorMessageGeneric": "Przepraszamy, nie możemy wyświetlić tej wizualizacji",
    "visualization.ErrorDescriptionGeneric": "Skontaktuj się z administratorem.",
    "visualization.ErrorMessageDataTooLarge": "Zbyt wiele punktów danych do wyświetlenia",
    "visualization.ErrorDescriptionDataTooLarge": "Spróbuj zastosować filtry.",
    "visualization.ErrorMessageNoData": "Brak danych",
    "visualization.ErrorDescriptionNoData": "Brak danych dla wybranego filtra.",
    "visualization.ErrorMessageKpi": "Błąd",
    "visualization.ErrorMessageUnauthorized": "Nieautoryzowany",
    "visualization.ErrorDescriptionUnauthorized": "Przepraszamy, nie masz dostępu do tej wizualizacji. Zaloguj się lub poproś administratora o nadanie uprawnień.",
    "visualization.ErrorMessageNotFound": "Przepraszamy, nie możemy znaleźć tej wizualizacji",
    "visualization.ErrorDescriptionNotFound": "Wizualizacja z tym adresem URL nie istnieje.",
    "visualization.ErrorDescriptionMissingMapboxToken": "Konfiguracja Geochart wymaga ważnego tokenu dostępu API.",
    "visualization.tooltip.resetZoom": "Resetuj powiększenie",
    "visualization.tooltip.interaction": "Kliknij wykres, aby przewijać",
    "visualization.tooltip.generic.interaction": "Kliknij, aby przewijać lub filtrować",
    "gs.filterLabel.all": "Wszystko",
    "gs.filterLabel.none": "Brak",
    "gs.filter.loading": "Ładowanie filtra…",
    "gs.filter.error": "Błąd podczas ładowania filtra.",
    "gs.filter.error.tooltip": "Błąd. Nie można załadować wartości.",
    "gs.list.clear": "Wyczyść",
    "gs.list.cancel": "Anuluj",
    "gs.list.apply": "Zastosuj",
    "gs.list.only": "Tylko",
    "gs.list.selectAll": "Zaznacz wszystko",
    "gs.list.limitExceeded": "Przepraszamy, przekroczyłeś limit ({limit})",
    "gs.list.limitReached": "Osiągnięto limit {limit} wybranych wartości.",
    "gs.list.cannotSelectMoreValues": "Nie można wybrać więcej niż {limit} wartości.",
    "gs.list.noItemsFound": "Nie znaleziono elementów.",
    "gs.list.noResultsMatch": "Brak pasujących wyników",
    "gs.list.error": "Błąd podczas ładowania wartości filtra.",
    "gs.header.upsellButtonText": "Aktualizacja",
    "gs.header.invite": "Zaproś",
    "gs.header.countdown.numberOfDaysLeft": "{number} dni pozostałe",
    "gs.header.countdown.numberOfMonthsLeft": "{number} pozostało miesięcy",
    "gs.header.countdown.oneMonthLeft": "Pozostał 1 miesiąc",
    "gs.header.countdown.lastDay": "To jest Twój ostatni dzień",
    "measure.title.suffix.same_period_year_ago": "SP rok temu",
    "measure.title.suffix.previous_period": "okres temu",
    "visualizations.measure.arithmetic.sum.title": "Suma {firstMeasureTitle} i {secondMeasureTitle}",
    "visualizations.measure.arithmetic.difference.title": "Różnica między {firstMeasureTitle} a {secondMeasureTitle}",
    "visualizations.measure.arithmetic.multiplication.title": "Iloczyn {firstMeasureTitle} i {secondMeasureTitle}",
    "visualizations.measure.arithmetic.ratio.title": "Wskaźnik {firstMeasureTitle} i {secondMeasureTitle}",
    "visualizations.measure.arithmetic.change.title": "Zmień z {secondMeasureTitle} na {firstMeasureTitle}",
    "visualizations.legend.text.top": "Góra",
    "visualizations.legend.text.bottom": "Dół",
    "visualizations.legend.text.left": "Lewo",
    "visualizations.legend.text.right": "Prawo",
    "visualizations.legend.text.colon": ":",
    "visualizations.legend.text.column": "Kolumna",
    "visualizations.legend.text.line": "Linia",
    "visualizations.legend.text.area": "Obszar",
    "visualizations.legend.text.combo": "{0} ({1})",
    "visualizations.menu.aggregations": "Agregacja",
    "visualizations.menu.aggregations.rows": "Wiersze",
    "visualizations.menu.aggregations.columns": "Kolumny",
    "visualizations.menu.aggregations.all-rows": "ze wszystkich wierszy",
    "visualizations.menu.aggregations.all-columns": "wszystkich kolumn",
    "visualizations.menu.aggregations.within-attribute": "w obrębie {attributeName}",
    "apply": "Zastosuj",
    "cancel": "Anuluj",
    "save": "Zapisz",
    "loading": "Ładowanie…",
    "filtering": "Filtrowanie…",
    "dateFilterDropdown.title": "Zakres dat",
    "dateFilterDropdown.setDefault": "Ustaw domyślny filtr daty dla{nbsp}widzów:",
    "dateFilterDropdown.configuration": "Konfiguracja",
    "filters.thisMinute.title": "Ta minuta",
    "filters.lastMinute.title": "Ostatnia minuta",
    "filters.nextMinute.title": "Następna minuta",
    "filters.thisHour.title": "Ta godzina",
    "filters.lastHour.title": "Ostatnia godzina",
    "filters.nextHour.title": "Następna godzina",
    "filters.thisDay.title": "Dzisiaj",
    "filters.lastDay.title": "Wczoraj",
    "filters.nextDay.title": "Jutro",
    "filters.thisWeek.title": "Ten tydzień",
    "filters.lastWeek.title": "W zeszłym tygodniu",
    "filters.nextWeek.title": "W przyszłym tygodniu",
    "filters.thisMonth.title": "Ten miesiąc",
    "filters.lastMonth.title": "W zeszłym miesiącu",
    "filters.nextMonth.title": "W przyszłym miesiącu",
    "filters.thisQuarter.title": "Ten kwartał",
    "filters.lastQuarter.title": "Ostatni kwartał",
    "filters.nextQuarter.title": "Następny kwartał",
    "filters.thisYear.title": "Ten rok",
    "filters.lastYear.title": "W zeszłym roku",
    "filters.nextYear.title": "Przyszły rok",
    "filters.lastNMinutes": "{n, plural, one {Ostatnia # minuta} other {Ostatnie # minuty}}",
    "filters.lastNHours": "{n, plural, one {Ostatnia # godzina} other {Ostatnie # godziny}}",
    "filters.lastNDays": "{n, plural, one {Ostatni # dzień} other {Ostatnie # dni}}",
    "filters.lastNWeeks": "{n, plural, one {Ostatni # tydzień} other {Ostatnie # tygodnie}}",
    "filters.lastNMonths": "{n, plural, one {Ostatni # miesiąc} other { Ostatnie # miesiące}}",
    "filters.lastNQuarters": "{n, plural, one {Ostatni # kwartał} other { Ostatnie # kwartały}}",
    "filters.lastNYears": "{n, plural, one {Ostatni # rok} other {Ostatnie # lata}}",
    "filters.nextNMinutes": "{n, plural, one {Następna # minuta} other {Następne # minuty}}",
    "filters.nextNHours": "{n, plural, one {Następna # godzina} other {Następne # godziny}}",
    "filters.nextNDays": "{n, plural, one {Następny # dzień} other { Następne # dni}}",
    "filters.nextNWeeks": "{n, plural, one {Następny # tydzień} other {Następne # tygodnie}}",
    "filters.nextNMonths": "{n, plural, one {Następny # miesiąc} other {Następne # miesiące}}",
    "filters.nextNQuarters": "{n, plural, one {Następny # kwartał} other {Następne # kwartały}}",
    "filters.nextNYears": "{n, plural, one {Następny # rok} other {Następne # lata}}",
    "filters.interval.minutes.past": "Od {from} do {to} {to, plural, one {minuty} other {minut}} temu",
    "filters.interval.minutes.past.sameValue": "{value} {value, plural, one {minuta} other {minuty}} temu",
    "filters.interval.minutes.future": "Od {from} do {to} {to, plural, one {minuta} other {minuty}} do przodu",
    "filters.interval.minutes.future.sameValue": "{value} {value, plural, one {minuta} other {minuty}} do przodu",
    "filters.interval.minutes.mixed": "Od {from} {from, plural, one {minuty} other {minut}} temu do {to} {to, plural, one {minuty} other {minut}} do przodu",
    "filters.interval.hours.past": "Od {from} do {to} {to, plural, one {godziny} other {godzin}} temu",
    "filters.interval.hours.past.sameValue": "{value} {value, plural, one {godzina} other {godziny}} temu",
    "filters.interval.hours.future": "Od {from} do {to} {to, plural, one {godziny} other {godzin}} do przodu",
    "filters.interval.hours.future.sameValue": "{value} {value, plural, one {godzina} other {godziny}} do przodu",
    "filters.interval.hours.mixed": "Od {from} {from, plural, one {godziny} other {godzin}} temu do {to} {to, plural, one {godziny} other {godzin}} do przodu",
    "filters.interval.days.past": "Od {from} do {to} {to, plural, one {dnia} other {dni}} temu",
    "filters.interval.days.past.sameValue": "{value} {value, plural, one {dzień} other {dni}} temu",
    "filters.interval.days.future": "Od {from} do {to} {to, plural, one {dni} other {dni}} do przodu",
    "filters.interval.days.future.sameValue": "{value} {value, plural, one {dzień} other { dni}} temu",
    "filters.interval.days.mixed": "Od {from} {from, plural, one {dnia} other {dni}} temu do {to} {to, plural, one {dnia} other {dni}} do przodu",
    "filters.interval.weeks.past": "Od {from} do {to} {to, plural, one {tygodnia} other {tygodni}} temu",
    "filters.interval.weeks.past.sameValue": "{value} {value, plural, one {tydzień} other {tygodnie}} temu",
    "filters.interval.weeks.future": "Od {from} do {to} {to, plural, one {tygodnia} other {tygodni}} do przodu",
    "filters.interval.weeks.future.sameValue": "{value} {value, plural, one {tydzień} other {tygodnie}} do przodu",
    "filters.interval.weeks.mixed": "Od {from} {from, plural, one {tygodnia} other {tygodni}} temu do {to} {to, plural, one {tygodnia} other {tygodni}} do przodu",
    "filters.interval.months.past": "Od {from} do {to} {to, plural, one {miesiąca} other {miesięcy}} temu",
    "filters.interval.months.past.sameValue": "{value} {value, plural, one {miesiąc} other {miesiące}} temu",
    "filters.interval.months.future": "Od {from} do {to} {to, plural, one {miesiąca} other {miesięcy}} do przodu",
    "filters.interval.months.future.sameValue": "{value} {value, plural, one {miesiąc} other {miesiące}} do przodu",
    "filters.interval.months.mixed": "Od {from} {from, plural, one {miesiąca} other {miesięcy}} temu do {to} {to, plural, one {miesiąca} other {miesięcy}} do przodu",
    "filters.interval.quarters.past": "Z {from} do {to} {to, plural, one {kwartał} other { kwartałów}} temu",
    "filters.interval.quarters.past.sameValue": "{value} {value, plural, one {kwartał} other { kwartałów}} temu",
    "filters.interval.quarters.future": "Od {from} do {to} {to, plural, one {kwartału} other {kwartały}} do przodu",
    "filters.interval.quarters.future.sameValue": "{value} {value, plural, one {kwartał} other {kwartały}} do przodu",
    "filters.interval.quarters.mixed": "Od {from} {from, plural, one {kwartału} other {kwartałów}} temu do {to} {to, plural, one {kwartału} other {kwartałów}} do przodu",
    "filters.interval.years.past": "Od {from} do {to} {to, plural, one {roku} other {lat}} temu",
    "filters.interval.years.past.sameValue": "{value} {value, plural, one {rok} other {lata}} temu",
    "filters.interval.years.future": "Od {from} do {to} {to, plural, one {roku} other {lat}} do przodu",
    "filters.interval.years.future.sameValue": "{value} {value, plural, one {rok} other {lata}} do przodu",
    "filters.interval.years.mixed": "Od {from} {from, plural, one {roku} other {lat}} temu do {to} {to, plural, one {roku} other {lat}} do przodu",
    "filters.granularity.minutes": "Minuty",
    "filters.granularity.hours": "Godziny",
    "filters.granularity.days": "Dni",
    "filters.granularity.weeks": "Tygodnie",
    "filters.granularity.months": "Miesiące",
    "filters.granularity.quarters": "Kwartały",
    "filters.granularity.years": "Lata",
    "filters.from": "z",
    "filters.to": "do",
    "filters.floatingRange": "Okres względny",
    "filters.floatingRange.noMatch": "Nie znaleziono dopasowania",
    "filters.floatingRange.tooBig": "Maksymalna wartość: {limit}",
    "filters.floatingRange.option.minute.offset.history": "{n, plural, one {ostatnia minuta} other {# minut temu}}",
    "filters.floatingRange.option.minute.offset.today": "ta minuta",
    "filters.floatingRange.option.minute.offset.future": "{n, plural, one {następna minuta} other {# minut do przodu}}",
    "filters.floatingRange.option.hour.offset.history": "{n, plural, one {ostatnia godzina} other {# godzin temu}}",
    "filters.floatingRange.option.hour.offset.today": "ta godzina",
    "filters.floatingRange.option.hour.offset.future": "{n, plural, one {następna godzina} other {# godzin do przodu}}",
    "filters.floatingRange.option.day.offset.history": "{n, plural, one {wczoraj} other {# dni temu}}",
    "filters.floatingRange.option.day.offset.today": "dzisiaj",
    "filters.floatingRange.option.day.offset.future": "{n, plural, one {jutro} other {# dni do przodu}}",
    "filters.floatingRange.option.week.offset.history": "{n, plural, one {zeszły tydzień} other {# tygodni temu}}",
    "filters.floatingRange.option.week.offset.today": "ten tydzień",
    "filters.floatingRange.option.week.offset.future": "{n, plural, one {następny tydzień} other {# tygodni do przodu}}",
    "filters.floatingRange.option.month.offset.history": "{n, plural, one {w zeszłym miesiącu} other {# miesięcy temu}}",
    "filters.floatingRange.option.month.offset.today": "ten miesiąc",
    "filters.floatingRange.option.month.offset.future": "{n, plural, one {następny miesiąc} other {# miesięcy do przodu}}",
    "filters.floatingRange.option.quarter.offset.history": "{n, plural, one {ostatni kwartał} other {# kwartały temu}}",
    "filters.floatingRange.option.quarter.offset.today": "ten kwartał",
    "filters.floatingRange.option.quarter.offset.future": "{n, plural, one {następny kwartał} other {# kwartały do przodu}}",
    "filters.floatingRange.option.year.offset.history": "{n, plural, one {w zeszłym roku} other {# lat temu}}",
    "filters.floatingRange.option.year.offset.today": "ten rok",
    "filters.floatingRange.option.year.offset.future": "{n, plural, one {przyszły rok} other {# lat do przodu}}",
    "filters.allTime.title": "Cały czas",
    "filters.allTime.excludeCurrentPeriod": "Wyklucz otwarty okres",
    "filters.minute.title": "MINUTA",
    "filters.minute.excludeCurrentPeriod": "Wyklucz tę minutę",
    "filters.hour.title": "GODZINA",
    "filters.hour.excludeCurrentPeriod": "Wyklucz tę godzinę",
    "filters.day.title": "DZIEŃ",
    "filters.day.excludeCurrentPeriod": "Wyklucz dzień dzisiejszy",
    "filters.week.title": "TYDZIEŃ",
    "filters.week.excludeCurrentPeriod": "Wyklucz ten tydzień",
    "filters.month.title": "MIESIĄC",
    "filters.month.excludeCurrentPeriod": "Wyklucz ten miesiąc",
    "filters.quarter.title": "KWARTAŁ",
    "filters.quarter.excludeCurrentPeriod": "Wyklucz ten kwartał",
    "filters.year.title": "ROK",
    "filters.year.excludeCurrentPeriod": "Wyklucz ten rok",
    "filters.excludeCurrentPeriod.unavailable": "Niedostępne dla wybranego zakresu dat",
    "filters.staticPeriod": "Okres statyczny",
    "filters.staticPeriod.incorrectFormat": "Data musi być w formacie {format}",
    "filters.staticPeriod.endDateBeforeStartDate": "Czas zakończenia musi być późniejszy niż czas rozpoczęcia",
    "mvf.operator.all": "wszystko",
    "mvf.operator.greaterThan": "więcej niż",
    "mvf.operator.greaterThanOrEqualTo": "większe lub równe",
    "mvf.operator.lessThan": "mniej niż",
    "mvf.operator.lessThanOrEqualTo": "mniejsze lub równe",
    "mvf.operator.equalTo": "równe",
    "mvf.operator.notEqualTo": "nie równa się",
    "mvf.operator.between": "pomiędzy",
    "mvf.operator.notBetween": "nie pomiędzy",
    "mvf.operator.between.tooltip.bubble": "Wartości początkowe i końcowe są uwzględnione.",
    "mvf.operator.notBetween.tooltip.bubble": "Wartości początkowe i końcowe nie są uwzględnione.",
    "mvf.treatNullValuesAsZeroLabel": "Traktuj puste wartości jako 0",
    "mvf.treatNullValuesAsZeroTooltip": "Jeśli warunek filtru obejmuje 0, puste wartości będą traktowane jako 0 i uwzględniane w obliczeniach.",
    "measureNumberFormat.custom.optionLabel": "Niestandardowy",
    "measureNumberFormat.buttonLabel": "Format: {selectedFormatPresetName}",
    "measureNumberCustomFormatDialog.title": "Format niestandardowy",
    "measureNumberCustomFormatDialog.template.preview.title": "Podgląd formatu",
    "measureNumberCustomFormatDialog.template.title": "Szablony",
    "measureNumberCustomFormatDialog.extendedPreview.button": "Pokaż więcej",
    "measureNumberCustomFormatDialog.howToFormat": "Jak formatować?",
    "measureNumberCustomFormatDialog.definition": "Definicja",
    "measureNumberCustomFormatDialog.preview": "Podgląd",
    "properties.legend.title": "Legenda",
    "attrf.all": "Wszystko",
    "attrf.all_except": "Wszystkie oprócz",
    "rankingFilter.topBottom": "Najwyższe/najniższe wartości",
    "rankingFilter.top": "Góra",
    "rankingFilter.bottom": "Dół",
    "rankingFilter.allRecords": "Wszystko",
    "rankingFilter.allRecords.tooltip": "Zastosuj filtr do wszystkich atrybutów w wizualizacji.",
    "rankingFilter.attributeDropdown.oneAttributeTooltip": "Wizualizacja jest podzielona tylko wg jednego atrybutu. Filtr zostanie zastosowany do wszystkich jego wartości.",
    "rankingFilter.outOf": "Z poza",
    "rankingFilter.basedOn": "Na podstawie",
    "rankingFilter.valueTooSmall": "Wartość wejściowa powinna być liczbą dodatnią.",
    "rankingFilter.valueTooLarge": "Wartość wejściowa jest zbyt duża.",
    "rankingFilter.preview": "Podgląd:",
    "rankingFilter.preview.top_without_attribute": "Najlepsze {value} z <strong>{measure}</strong>",
    "rankingFilter.preview.bottom_without_attribute": "Dolne {value} z <strong>{measure}</strong>",
    "rankingFilter.preview.top_with_attribute": "Najlepsze {value} z <strong>{attribute}</strong> na podstawie <strong>{measure}</strong>",
    "rankingFilter.preview.bottom_with_attribute": "Dolne {value} z <strong>{attribute}</strong> na podstawie <strong>{measure}</strong>",
    "rankingFilter.valueTooltip": "Jeśli wiele elementów ma tę samą wartość, filtr pokazuje wszystkie elementy z tą wartością. Wizualizacja może wtedy wyświetlać więcej elementów niż ustawiona liczba.",
    "attributesDropdown.itemsFiltered.tooltip": "Wartości są filtrowane przez: <strong>{filters}</strong>",
    "attributesDropdown.itemsFiltered": "Elementy są filtrowane",
    "attributeFilterDropdown.emptyValue": "pusta wartość",
    "attributesDropdown.noData": "Ten atrybut nie ma wartości.",
    "attributesDropdown.noResultsMatch": "Brak pasujących wyników.",
    "attributesDropdown.allItemsFiltered": "Wszystkie wartości są odfiltrowane.",
    "attributesDropdown.configuration": "Konfiguracja",
    "attributesDropdown.removeTooltip": "Usuń z pulpitu nawigacyjnego",
    "attributesDropdown.display_as": "Wyświetl jako: {title}",
    "attributesDropdown.empty.item.tooltip": "Uwzględnij brakujące (null) i puste (\"\") wartości.",
    "attributesDropdown.filterConfiguredMessage": "<strong>{parentTitle}</strong> jest już filtrowany przez <strong>{childTitle}</strong> bezpośrednio lub poprzez inne filtry.",
    "attributesDropdown.attributeNameWithData": "z danymi o",
    "attributesDropdown.noConnectionMessage": "<strong>{childTitle}</strong> nie można filtrować za pomocą <strong>{parentTitle}</strong>. W modelu danych nie ma połączenia między atrybutami filtra.",
    "attributesDropdown.details.type": "Atrybut",
    "attributesDropdown.details.dataset": "Zestaw danych",
    "attributesDropdown.relevantValues": "Tylko istotne wartości.{nbsp}",
    "attributesDropdown.relevantValues.tooltip.parentFilters": "Dostępne wartości dla <strong>{child}</strong> są filtrowane wg wybranych <strong>{parents}</strong>.",
    "attributesDropdown.relevantValues.tooltip.limits": "Wartości dla <strong>{child}</strong> są filtrowane przez dodatkowe ustawienie filtra.",
    "attributesDropdown.relevantValues.tooltip.parentFiltersLimits": "Wartości dla <strong>{child}</strong> są filtrowane przez wybrane <strong>{parents}</strong> oraz dodatkowe ustawienie filtra.",
    "attributesDropdown.noRelevantValues": "Brak odpowiednich wartości",
    "attributesDropdown.noRelevantValues.tooltip": "Twój wybór w filtrze zależnym nie spowodował dopasowania żadnych wartości dla tego filtra.{break}Kliknij „Pokaż wszystkie”, aby zobaczyć wszystkie dostępne opcje.",
    "attributesDropdown.irrelevantValues": "Wybrano nieistotną wartość.{nbsp}",
    "attributesDropdown.irrelevantValues.tooltip": "Wybrana wartość nie jest już istotna z powodu zmian w <strong>{parents}</strong>.",
    "attributesDropdown.irrelevantValues.clear": "Wyczyść",
    "attributesDropdown.showAll": "Pokaż wszystko",
    "shareDialog.share.grantee.title": "Udostępnij użytkownikom i grupom",
    "shareDialog.share.grantee.share": "Udostępnij",
    "shareDialog.share.grantee.list.title": "Udostępnione dla",
    "shareDialog.share.grantee.add": "Dodaj",
    "shareDialog.share.grantee.add.empty.selection": "Nie wybrano użytkownika ani grupy.",
    "shareDialog.share.grantee.add.info": "Dodaj użytkowników i grupy",
    "shareDialog.share.grantee.add.search.placeholder": "Wyszukaj użytkowników i grupy",
    "shareDialog.share.grantee.add.search.error.message": "Nie udało się załadować użytkowników i grup. Spróbuj ponownie później.",
    "shareDialog.share.grantee.add.label.user": "Użytkownicy",
    "shareDialog.share.grantee.add.label.group": "Grupy",
    "shareDialog.share.grantee.add.search.no.matching.items": "Brak pasujących użytkowników lub grup",
    "shareDialog.share.grantee.item.you": "{userName} (Ty)",
    "shareDialog.share.grantee.item.users.count": "{granteeCount} użytkownicy",
    "shareDialog.share.grantee.item.creator": "Twórca",
    "shareDialog.share.grantee.item.user.all": "Wszyscy użytkownicy",
    "shareDialog.share.grantee.item.user.inactive": "Nieaktywny użytkownik",
    "shareDialog.share.grantee.item.user.inactive.description": "Użytkownik został usunięty z tego obszaru roboczego",
    "shareDialog.share.grantee.item.remove.selection": "Usuń z wyboru.",
    "shareDialog.share.granular.grantee.permission.edit": "Może edytować i udostępniać",
    "shareDialog.share.granular.grantee.permission.share": "Może przeglądać i udostępniać",
    "shareDialog.share.granular.grantee.permission.view": "Może wyświetlać",
    "shareDialog.share.granular.grantee.permission.remove": "Usuń",
    "shareDialog.share.granular.granularUser.tooltip.cannotChangeHigher": "Nie możesz usunąć ani zmienić uprawnień użytkowników z wyższymi uprawnieniami niż Twoje.",
    "shareDialog.share.granular.granularGroup.tooltip.cannotChangeHigher": "Nie możesz usuwać ani zmieniać uprawnień dla grup z wyższymi uprawnieniami niż posiadasz.",
    "shareDialog.share.granular.grantee.tooltip.cannotGrantHigher": "Nie możesz ustawić wyższych uprawnień niż posiadasz.",
    "shareDialog.share.granular.granularUser.tooltip.cannotGrantLower": "Nie można ustawić niższych uprawnień niż uprawnienia z grup użytkowników dla tego użytkownika.",
    "shareDialog.share.granular.granularGroup.tooltip.cannotGrantLower": "Nie można ustawić niższych uprawnień niż uprawnienia z grup użytkowników, które zawierają tę grupę.",
    "shareDialog.share.granular.granularUser.tooltip.cannotRemoveFromParent": "Nie można usunąć uprawnień dla tego użytkownika w tym obszarze roboczym. Aby usunąć uprawnienia, należy to zrobić z poziomu nadrzędnego obszaru roboczego.",
    "shareDialog.share.granular.granularGroup.tooltip.cannotRemoveFromParent": "Nie można usunąć uprawnień dla tej grupy użytkowników w tym obszarze roboczym. Aby usunąć uprawnienia, zrób to z poziomu nadrzędnego obszaru roboczego.",
    "shareDialog.share.granular.granularUser.tooltip.noChangeAvailable": "Nie można usunąć ani zmienić uprawnień dla tego użytkownika w tym obszarze roboczym. Aby edytować uprawnienia, należy to zrobić z poziomu nadrzędnego obszaru roboczego.",
    "shareDialog.share.granular.granularGroup.tooltip.noChangeAvailable": "Nie można usunąć ani zmienić uprawnień dla tej grupy użytkowników w tym obszarze roboczym. Aby edytować uprawnienia, należy to zrobić z poziomu nadrzędnego obszaru roboczego.",
    "shareDialog.share.granular.administrator.info": "<b>Uwaga.</b> Ty i inni administratorzy macie pełny dostęp do wszystkich pulpitów nawigacyjnych.",
    "sorting.dropdown.header": "Sortuj wizualizację",
    "sorting.type.alphabetical.asc": "Od A do Z",
    "sorting.type.alphabetical.desc": "Od Z do A",
    "sorting.type.date.asc": "Od najstarszego do najnowszego",
    "sorting.type.date.desc": "Od najnowszego do najstarszego",
    "sorting.type.default": "Domyślnie",
    "sorting.type.numerical.asc": "Od najmniejszego do największego",
    "sorting.type.numerical.desc": "Od największego do najmniejszego",
    "sorting.by": "przez",
    "sorting.sum.of.all.measure": "Suma",
    "sorting.default.tooltip": "Użyj kolejności zdefiniowanej w atrybucie.",
    "embedInsightDialog.actions.close": "Zamknij",
    "embedInsightDialog.actions.copyCode": "Skopiuj kod",
    "embedInsightDialog.component.type": "Typ komponentu",
    "embedInsightDialog.code.language.codeAs": "Koduj jako",
    "embedInsightDialog.react.options": "Inne opcje",
    "embedInsightDialog.webComponents.options": "Opcje",
    "embedInsightDialog.webComponents.options.displayTitle": "Wyświetl tytuł",
    "embedInsightDialog.webComponents.options.customTitle": "Niestandardowy tytuł",
    "embedInsightDialog.webComponents.options.locale": "Lokalizacja",
    "embedInsightDialog.webComponents.locale.tooltip": "Wybierz konkretną lokalizację językową. Jeśli jest wyłączona, wizualizacja domyślnie używa bieżących ustawień języka wyświetlania.",
    "embedInsightDialog.code.options.include.config.info": "Uwzględnij konfigurację wizualizacji kolorów, osi, legendy i płótna, jeśli są dostępne.",
    "embedInsightDialog.code.options.custom.height": "Wysokość niestandardowa",
    "embedInsightDialog.code.options.display.configuration": "Uwzględnij konfigurację",
    "embedInsightDialog.headLine.embedInsight": "Osadź wizualizację",
    "embedInsightDialog.componentType.byReference.tooltip": "Osadź jako odniesienie do zapisanej wizualizacji w ogólnym komponencie react GD.UI. Wszelkie przyszłe zmiany wizualizacji (takie, jak typ wizualizacji, metryki, atrybuty) będą odzwierciedlone w osadzonej wersji.",
    "embedInsightDialog.componentType.byDefinition.tooltip": "Osadź jako definicję wizualizacji w określonym komponencie GD.UI react na podstawie aktualnie wybranego typu wizualizacji. Żadne przyszłe zmiany wizualizacji (takie, jak typ wizualizacji, metryki, atrybuty) dokonane w tej aplikacji nie będą odzwierciedlone w osadzonej wersji.",
    "embedInsightDialog.webComponents.customTitle.tooltip": "Zdefiniuj tekst tytułu bezpośrednio w fragmencie kodu.",
    "embedInsightDialog.webComponents.customTitle.disabled.tooltip": "Najpierw włącz wyświetlanie tytułu.",
    "embedInsightDialog.prepareEnvironmentMessage": "<b>Uwaga.</b> Aby ten fragment działał, przygotuj swoje środowisko.",
    "embedInsightDialog.prepareEnvironmentMessage.link": "Dowiedz się więcej",
    "embed.dialog.numeric.input.validation": "Wartość musi być liczbą większą niż 0",
    "embed.dialog.numeric.input.warning": "To pole przyjmuje tylko cyfry większe niż 0",
    "embedInsightDialog.complete.list.props.message": "Pełna lista właściwości osadzania",
    "embedInsightDialog.emptyInsight.byReference": "Fragment kodu zostanie wyświetlony tutaj po <a>zapisaniu wizualizacji</a>.",
    "embedInsightDialog.emptyInsight.byDefinition": "Ten typ wizualizacji nie może być osadzony jako komponent typu programistycznego.",
    "embedDialog.tab.react": "Reaguj",
    "embedDialog.tab.webComponents": "Komponenty sieciowe",
    "error.overlay.login": "Zaloguj się",
    "error.overlay.title": "Zostałeś wylogowany",
    "error.overlay.text": "Proszę zalogować się ponownie, aby kontynuować pracę.",
    "stylingPicker.title.basic": "Domyślnie",
    "stylingPicker.title.custom": "Niestandardowy",
    "stylingPicker.title.create": "Utwórz",
    "stylingEditor.dialog.name": "Nazwa",
    "stylingEditor.dialog.name.required": "Nie można zapisać. Podaj nazwę.",
    "stylingEditor.dialog.definition": "Definicja",
    "stylingEditor.dialog.definition.required": "Nie można zapisać. Określ definicję.",
    "stylingEditor.dialog.definition.invalid": "Nie można zapisać. Definicja nie jest prawidłowym obiektem JSON.",
    "stylingEditor.dialog.examples": "Szablony",
    "stylingEditor.dialog.example.paste": "Wklej",
    "stylingPicker.item.edit": "Edytuj",
    "stylingPicker.item.delete": "Usuń",
    "stylingPicker.item.delete.tooltip": "Zastosowany element nie może zostać usunięty.",
    "descriptionPanel.button.more": "Pokaż więcej",
    "descriptionPanel.button.less": "Pokaż mniej",
    "configurationPanel.drillConfig.learn.more.link": "Dowiedz się więcej",
    "configurationPanel.drillConfig.drillToDashboard.tooltip": "Otwórz powiązany pulpit nawigacyjny, aby uzyskać rozszerzony widok wybranego punktu danych, przenosząc odpowiednie filtry i kontekst. <a>Dowiedz się więcej</a>",
    "configurationPanel.drillConfig.drillToInsight.tooltip": "Otwórz powiązaną wizualizację, zachowując zastosowane filtry z oryginalnego widoku. <a>Dowiedz się więcej</a>",
    "configurationPanel.drillConfig.drillToUrl.tooltip": "Otwórz niestandardowy URL z dynamicznymi parametrami na podstawie wybranego punktu danych. <a>Dowiedz się więcej</a>",
    "configurationPanel.drillConfig.drilldown": "Przewijanie w dół",
    "configurationPanel.drillConfig.drilldown.tooltip": "Przewijanie w dół w bieżącej wizualizacji, podążając za zdefiniowanymi hierarchiami atrybutów, aby zobaczyć swoje dane na coraz bardziej szczegółowym poziomie. <a>Dowiedz się więcej</a>",
    "configurationPanel.drillConfig.drilldown.tooltip.disabled.insight": "Przewijanie w dół jest wyłączony w konfiguracji tej wizualizacji.",
    "configurationPanel.drillConfig.drilldown.tooltip.disabled.metric": "Przewijanie w dół można ustawić tylko dla atrybutów, nie dla metryk.",
    "configurationPanel.drillConfig.drilldown.emtpy.hierarchy.info": "Atrybut musi znajdować się w hierarchii, aby umożliwić przewijanie w dół.",
    "configurationPanel.drillConfig.selectHierarchy": "Wybierz hierarchię…",
    "configurationPanel.drillConfig.drilldown.create.hierarchy": "Utwórz hierarchię atrybutów",
    "attributeHierarchyEditor.untitled": "Hierarchia atrybutów bez tytułu",
    "attributeHierarchyEditor.hierarchy.levels": "Poziomy hierarchii",
    "attributeHierarchyEditor.button.cancel": "Anuluj",
    "attributeHierarchyEditor.button.create": "Utwórz hierarchię",
    "attributeHierarchyEditor.button.save": "Zapisz zmiany",
    "attributeHierarchyEditor.button.delete": "Usuń",
    "attributeHierarchyEditor.delete.confirm.title": "Usunąć hierarchię atrybutów?",
    "attributeHierarchyEditor.delete.confirm.message": "Wszystkie istniejące interakcje przewijania w dół wykorzystujące tę hierarchię zostaną usunięte.",
    "attributeHierarchyEditor.remove.attribute": "Usuń",
    "attributeHierarchyEditor.add.attribute": "Dodaj atrybut",
    "attributeHierarchyEditor.add.attribute.above": "Dodaj atrybut powyżej",
    "attributeHierarchyEditor.add.attribute.bellow": "Dodaj atrybut poniżej",
    "attributeHierarchyEditor.howToWork.link": "Jak pracować z hierarchiami",
    "attributeHierarchyEditor.attribute.dropdown.title": "Wybierz atrybut…",
    "attributeHierarchyEditor.attribute.dropdown.search": "Szukaj…",
    "attributeHierarchyEditor.note.title": "Notatka:",
    "attributeHierarchyEditor.note.message": "<b>Notatka:</b> Zdefiniowana przez Ciebie hierarchia atrybutów jest stosowana globalnie do wszystkich wizualizacji. Umożliwia to interakcje przewijania w dół nie tylko dla {br}bieżącej wizualizacji, ale dla wszystkich wizualizacji, które zawierają dowolny atrybut w ramach hierarchii.",
    "attributeHierarchyEditor.howItWorks.title": "Jak to działa",
    "attributeHierarchyEditor.howItWorks.message.heading": "Hierarchia jest stosowana do wszystkich wizualizacji.",
    "attributeHierarchyEditor.message.create.success": "Świetnie! Utworzyliśmy hierarchię atrybutów!",
    "attributeHierarchyEditor.message.update.success": "Świetnie! Zapisaliśmy hierarchię atrybutów!",
    "attributeHierarchyEditor.message.delete.success": "Świetnie! Usunęliśmy hierarchię atrybutów!",
    "attributeHierarchyEditor.message.create.failed": "Nie udało się utworzyć. Spróbuj ponownie później.",
    "attributeHierarchyEditor.message.update.failed": "Nie udało się zapisać. Spróbuj ponownie później.",
    "attributeHierarchyEditor.message.delete.failed": "Nie udało się usunąć. Spróbuj ponownie później.",
    "attributeHierarchyEditor.howItWorks.message.content": "Interakcja przewijania w dół zostanie włączona nie tylko dla tej wizualizacji, ale dla wszystkich wizualizacji zawierających jeden z atrybutów w hierarchii.",
    "attributeHierarchyList.tooltip.generic.date.title": "Ogólna data",
    "attributeHierarchyList.tooltip.generic.date.info": "Ta hierarchia jest generowana automatycznie i dotyczy każdej wymiaru daty.",
    "attributeHierarchyList.tooltip.hierarchy.levels": "Poziomy hierarchii",
    "attributeHierarchyList.tooltip.button.edit": "Edytuj",
    "catalog.attribute.tooltip.hierarchy.title": "Hierarchia",
    "visualizationConfig.interactions.section.title": "Interakcje",
    "visualizationConfig.interactions.section.drilldown": "Przewijanie w dół",
    "workspaceHierarchy.lockedInsight": "Tylko administratorzy mogą zapisywać zmiany w tej wizualizacji.",
    "workspaceHierarchy.inheritedInsight": "Nie możesz edytować ani usuwać tej wizualizacji.{br}Jest centralnie zarządzana i certyfikowana.",
    "userManagement.workspace.noMatchingItems": "Brak pasujących przestrzeni roboczych.",
    "userManagement.workspace.searchPlaceholder": "Wyszukaj przestrzenie robocze",
    "userManagement.workspace.searchError": "Nie udało się załadować przestrzeni roboczych. Spróbuj ponownie później.",
    "userManagement.dataSource.searchError": "Nie udało się załadować źródeł danych. Spróbuj ponownie później.",
    "userManagement.workspace.emptySelection.user.view": "Ten użytkownik nie ma uprawnień do żadnych przestrzeni roboczych.",
    "userManagement.workspace.emptySelection.userGroup.view": "Ta grupa nie ma uprawnień do żadnych przestrzeni roboczych.",
    "userManagement.workspace.emptySelection.edit": "Nie wybrano przestrzeni roboczej.",
    "userManagement.workspace.title": "Dodaj uprawnienia do przestrzeni roboczej",
    "userManagement.dataSource.searchPlaceholder": "Wyszukaj źródła danych",
    "userManagement.workspace.addButton": "Dodaj",
    "userManagement.userGroups.addButton": "Dodaj",
    "userManagement.userGroups.cancelButton": "Anuluj",
    "userManagement.tab.workspaces": "Przestrzenie robocze ({count})",
    "userManagement.tab.groups": "Grupy ({count})",
    "userManagement.tab.users": "Członkowie ({count})",
    "userManagement.tab.details": "Szczegóły",
    "userManagement.buttons.addWorkspace": "Dodaj uprawnienia do przestrzeni roboczej",
    "userManagement.buttons.addToGroup": "Dodaj do grupy",
    "userManagement.buttons.addUser": "Dodaj członków",
    "userManagement.buttons.edit": "Edytuj",
    "userManagement.dataSource.title": "Dodaj uprawnienia do źródła danych",
    "userManagement.tab.dataSources": "Źródła danych ({count})",
    "userManagement.buttons.addDataSourcePermission": "Dodaj uprawnienia do źródła danych",
    "userManagement.dataSources.emptySelection.view": "Ten użytkownik nie ma uprawnień do żadnych źródeł danych.",
    "userManagement.dataSources.emptySelection.userGroup.view": "Ta grupa nie ma uprawnień do żadnych źródeł danych.",
    "userManagement.dataSources.emptySelection.edit": "Nie wybrano źródeł danych.",
    "userManagement.dataSources.permission.manage": "Zarządzaj",
    "userManagement.dataSources.permission.use": "Użyj",
    "userManagement.dataSources.permission.remove": "Usuń",
    "userManagement.dataSources.noMatchingItems": "Brak pasującego źródła danych.",
    "userManagement.users.multipleDataSources.addSuccess": "Świetnie! Pomyślnie dodałeś uprawnienia użytkownikom.",
    "userManagement.userGroups.multipleDataSources.addSuccess": "Świetnie! Pomyślnie dodałeś uprawnienia do grup.",
    "userManagement.users.multipleDataSources.addError": "Nie udało się dodać uprawnienia użytkownikom.",
    "userManagement.userGroups.multipleDataSources.addError": "Nie udało się dodać uprawnienia do grup.",
    "userManagement.dataSources.removeSuccess": "Świetnie! Pomyślnie usunięto uprawnienia do źródła danych.",
    "userManagement.dataSources.removeError": "Usunięcie uprawnień do źródła danych nie powiodło się.",
    "userManagement.dataSources.changeSuccess": "Świetnie! Pomyślnie zmieniłeś uprawnienia źródła danych.",
    "userManagement.dataSources.changeError": "Nie udało się zmienić uprawnień do źródła danych.",
    "userManagement.users.deleteLink": "Usuń użytkownika",
    "userManagement.userGroups.deleteLink": "Usuń grupę",
    "userManagement.closeButton": "Zamknij",
    "userManagement.workspace.removeSuccess": "Świetnie! Pomyślnie usunięto uprawnienie.",
    "userManagement.workspace.removeError": "Usunięcie uprawnienia nie powiodło się.",
    "userManagement.workspace.addSuccess": "Świetnie! Pomyślnie dodano uprawnienia do przestrzeni roboczej.",
    "userManagement.workspace.addError": "Dodanie uprawnień do przestrzeni roboczej nie powiodło się.",
    "userManagement.dataSource.addSuccess": "Świetnie! Pomyślnie dodano uprawnienia do źródła danych.",
    "userManagement.dataSource.addError": "Dodanie uprawnień do źródła danych nie powiodło się.",
    "userManagement.users.multipleWorkspaces.addSuccess": "Świetnie! Pomyślnie dodałeś uprawnienia do przestrzeni roboczej dla użytkowników.",
    "userManagement.users.multipleWorkspaces.addError": "Nie udało się dodać uprawnień do przestrzeni roboczej dla użytkowników.",
    "userManagement.userGroups.multipleWorkspaces.addSuccess": "Świetnie! Pomyślnie dodałeś uprawnienia do przestrzeni roboczej dla grup.",
    "userManagement.userGroups.multipleWorkspaces.addError": "Nie udało się dodać uprawnień do przestrzeni roboczej dla grup.",
    "userManagement.workspace.changeSuccess": "Świetnie! Pomyślnie zmieniłeś uprawnienia do przestrzeni roboczej.",
    "userManagement.workspace.changeError": "Nie udało się zmienić uprawnień do przestrzeni roboczej.",
    "userManagement.workspace.hierarchicalPermission.yes": "Uwzględnij podhierarchię",
    "userManagement.workspace.hierarchicalPermission.yes.tooltip": "Zastosuj uprawnienia do tego obszaru roboczego i wszystkich jego podrzędnych obszarów roboczych.",
    "userManagement.workspace.hierarchicalPermission.no": "To miejsce pracy",
    "userManagement.workspace.hierarchicalPermission.no.tooltip": "Zastosuj uprawnienie tylko do tego obszaru roboczego.",
    "userManagement.workspace.permission.view": "Widok",
    "userManagement.workspace.permissionUser.view.tooltip": "Użytkownik może przeglądać pulpity nawigacyjne, które zostały z nim udostępnione.",
    "userManagement.workspace.permissionGroup.view.tooltip": "Członkowie grupy mogą przeglądać pulpity nawigacyjne, które zostały udostępnione grupie.",
    "userManagement.dataSources.permissionUser.use.tooltip": "Użytkownik może korzystać ze źródeł danych, które zostały z nim udostępnione.",
    "userManagement.dataSources.permissionGroup.use.tooltip": "Członkowie grupy mogą korzystać ze źródeł danych, które zostały udostępnione grupie.",
    "userManagement.workspace.permission.viewExport": "Wyświetl i Eksportuj",
    "userManagement.workspace.permissionUser.viewExport.tooltip": "Obejmuje uprawnienie do przeglądania. Dodatkowo użytkownik może eksportować pulpit nawigacyjny do plików PDF oraz dane tabelaryczne z wizualizacji do plików XLSX i CSV.",
    "userManagement.workspace.permissionGroup.viewExport.tooltip": "Obejmuje uprawnienie do przeglądania. Dodatkowo, członkowie grupy mogą eksportować pulpit nawigacyjny do plików PDF oraz dane tabelaryczne z wizualizacji do plików XLSX i CSV.",
    "userManagement.workspace.permission.analyze": "Analizuj",
    "userManagement.workspace.permissionUser.analyze.tooltip": "Obejmuje uprawnienia do przeglądania i zapisywania widoków. Dodatkowo użytkownik może tworzyć, edytować lub usuwać pulpity nawigacyjne i wizualizacje oraz przeglądać LDM i metryki.",
    "userManagement.workspace.permissionGroup.analyze.tooltip": "Obejmuje uprawnienia do przeglądania i zapisywania widoków. Dodatkowo, członkowie grupy mogą tworzyć, edytować lub usuwać pulpity nawigacyjne i wizualizacje oraz przeglądać LDM i metryki.",
    "userManagement.workspace.permission.analyzeExport": "Analizuj i Eksportuj",
    "userManagement.workspace.permissionUser.analyzeExport.tooltip": "Obejmuje uprawnienia do przeglądania i zapisywania widoków. Dodatkowo użytkownik może tworzyć, edytować lub usuwać pulpity nawigacyjne i wizualizacje oraz przeglądać LDM i metryki. Może również eksportować pulpity nawigacyjne do plików PDF oraz dane tabelaryczne z wizualizacji do plików XLSX i CSV.",
    "userManagement.workspace.permissionGroup.analyzeExport.tooltip": "Obejmuje uprawnienia do przeglądania i zapisywania widoków. Dodatkowo, członkowie grupy mogą tworzyć, edytować lub usuwać pulpity nawigacyjne i wizualizacje oraz przeglądać LDM i metryki. Mogą również eksportować pulpity nawigacyjne do plików PDF oraz dane tabelaryczne z wizualizacji do plików XLSX i CSV.",
    "userManagement.workspace.permission.manage": "Zarządzaj",
    "userManagement.workspace.permissionUser.manage.tooltip": "Obejmuje uprawnienia do przeglądania, analizowania, eksportowania i zapisywania widoków. Dodatkowo użytkownik może tworzyć, edytować lub usuwać logiczny model danych i metryki oraz ma nieograniczony dostęp do wszystkich pulpitów nawigacyjnych i ich uprawnień.",
    "userManagement.workspace.permissionGroup.manage.tooltip": "Obejmuje uprawnienia do przeglądania, analizowania, eksportowania i zapisywania widoków. Dodatkowo, członkowie grupy mogą tworzyć, edytować lub usuwać logiczny model danych i metryki oraz mają nieograniczony dostęp do wszystkich pulpitów nawigacyjnych i ich uprawnień.",
    "userManagement.dataSources.permissionUser.manage.tooltip": "Użytkownik może tworzyć, edytować lub usuwać źródła danych.",
    "userManagement.dataSources.permissionGroup.manage.tooltip": "Członkowie grupy mogą tworzyć, edytować lub usuwać źródła danych.",
    "userManagement.workspace.permission.remove": "Usuń",
    "userManagement.groupDetail.id.label": "ID",
    "userManagement.groupDetail.name.label": "Nazwa",
    "userManagement.userDetail.firstName.label": "Imię",
    "userManagement.userDetail.lastName.label": "Nazwisko",
    "userManagement.userDetail.email.label": "E-mail",
    "userManagement.userDetail.orgPermission.label": "Uprawnienia organizacji",
    "userManagement.detail.orgPermission.admin": "Administrator",
    "userManagement.detail.orgPermission.admin.tooltip": "Administrator organizacji. Ten użytkownik ma dostęp do każdej chronionej akcji lub zasobu.",
    "userManagement.detail.orgPermission.member": "Członek",
    "userManagement.detail.orgPermission.member.tooltip": "Członek organizacji. Ten użytkownik ma dostęp do działania lub zasobu, do którego ma uprawnienia.",
    "userManagement.userDetail.id.label": "ID",
    "userManagement.userDetail.emptyValue": "nie ustawiono",
    "userManagement.userGroups.emptySelection.view": "Ten użytkownik nie jest członkiem żadnej grupy.",
    "userManagement.userGroups.emptySelection.edit": "Nie wybrano grup.",
    "userManagement.userDetail.saveButton": "Zapisz",
    "userManagement.userDetail.cancelButton": "Anuluj",
    "userManagement.groupDetail.saveButton": "Zapisz",
    "userManagement.groupDetail.cancelButton": "Anuluj",
    "userManagement.userDetails.updatedSuccess": "Świetnie! Pomyślnie zmieniłeś szczegóły użytkownika.",
    "userManagement.userDetails.updatedFailure": "Zmiana danych użytkownika nie powiodła się.",
    "userManagement.groupDetails.updatedSuccess": "Świetnie! Pomyślnie zmieniłeś szczegóły grupy.",
    "userManagement.groupDetails.updatedFailure": "Zmiana grupy szczegółów użytkownika nie powiodła się.",
    "userManagement.userGroup.addSuccess": "Świetnie! Pomyślnie dodano grupę(y).",
    "userManagement.userGroup.addError": "Dodanie grup(y) nie powiodło się.",
    "userManagement.multipleUserGroup.addSuccess": "Świetnie! Pomyślnie dodano użytkowników do grupy.",
    "userManagement.multipleUserGroup.addError": "Nie udało się dodać użytkowników do grup.",
    "userManagement.userGroups.title": "Dodaj do grupy",
    "userManagement.userGroups.noMatchingItems": "Brak pasującej grupy.",
    "userManagement.userGroups.searchPlaceholder": "Wyszukaj grupy",
    "userManagement.userGroups.searchError": "Nie udało się załadować grup. Spróbuj ponownie później.",
    "userManagement.userGroup.removeSuccess": "Świetnie! Pomyślnie usunięto grupę.",
    "userManagement.userGroup.removeFailure": "Usunięcie grupy nie powiodło się.",
    "userManagement.userGroups.removeSuccess": "Świetnie! Pomyślnie usunięto grupę.",
    "userManagement.userGroups.removeFailure": "Usunięcie grupy nie powiodło się.",
    "userManagement.userGroups.removeTooltip": "Usuń grupę z użytkownika.",
    "userManagement.userGroups.removeDisabledTooltip": "Grupa nie może zostać usunięta od użytkownika.",
    "userManagement.deleteDialog.user.title": "Usunąć użytkownika?",
    "userManagement.deleteDialog.user.body": "Użytkownik zostanie nieodwracalnie usunięty, ale jego wizualizacje i pulpity nawigacyjne pozostaną nienaruszone.",
    "userManagement.deleteDialog.user.disabledTooltip": "Nie można usunąć użytkownika.",
    "userManagement.deleteDialog.userGroup.adminDisabledTooltip": "Ta grupa nie może zostać usunięta.",
    "userManagement.deleteDialog.userGroup.nonEmptyDisabledTooltip": "Nie można usunąć tej grupy, ponieważ zawiera członków.",
    "userManagement.deleteDialog.multipleUsers.title": "Usunąć użytkowników?",
    "userManagement.deleteDialog.multipleUsers.body": "<b>{count} użytkownicy</b> zostaną nieodwracalnie usunięte, ale ich wizualizacje i pulpity nawigacyjne pozostaną niezmienione.",
    "userManagement.deleteDialog.group.title": "Usunąć grupę?",
    "userManagement.deleteDialog.group.body": "Grupa zostanie nieodwracalnie usunięta. Wszyscy jej członkowie utracą prawa zdefiniowane przez uprawnienia grupy.",
    "userManagement.deleteDialog.multipleGroups.title": "Usunąć grupy?",
    "userManagement.deleteDialog.multipleGroups.body": "<b>{count} grupy </b> zostaną nieodwracalnie usunięte. Wszyscy ich członkowie utracą prawa zdefiniowane przez uprawnienia specyficzne dla grupy.",
    "userManagement.deleteDialog.cancelButton": "Anuluj",
    "userManagement.deleteDialog.confirmButton": "Usuń",
    "userManagement.userGroups.deleteSuccess": "Świetnie! Pomyślnie usunięto grupę.",
    "userManagement.userGroups.deleteFailure": "Usunięcie grupy nie powiodło się.",
    "userManagement.multipleUserGroups.deleteSuccess": "Świetnie! Pomyślnie usunięto grupy.",
    "userManagement.multipleUserGroups.deleteFailure": "Usunięcie grup nie powiodło się.",
    "userManagement.createUserGroup.createSuccess": "Świetnie! Pomyślnie utworzono grupę.",
    "userManagement.createUserGroup.createFailure": "Tworzenie grupy nie powiodło się.",
    "userManagement.users.loadingError.title": "Nie można otworzyć użytkownika",
    "userManagement.users.loadingError.notExist": "Użytkownik, którego próbujesz zobaczyć, nie istnieje.",
    "userManagement.users.loadingError.unknown": "Nie można załadować użytkownika, którego próbujesz zobaczyć.",
    "userManagement.userGroups.loadingError.title": "Nie można otworzyć grupy",
    "userManagement.userGroups.loadingError.notExist": "Grupa, którą próbujesz zobaczyć, nie istnieje.",
    "userManagement.userGroups.loadingError.unknown": "Grupa, którą próbujesz zobaczyć, nie może zostać załadowana.",
    "userManagement.users.deleteSuccess": "Świetnie! Użytkownik został pomyślnie usunięty.",
    "userManagement.users.deleteFailure": "Usunięcie użytkownika nie powiodło się.",
    "userManagement.multipleUsers.deleteSuccess": "Świetnie! Użytkownicy zostali pomyślnie usunięci.",
    "userManagement.multipleUsers.deleteFailure": "Usunięcie użytkowników nie powiodło się.",
    "userManagement.users.searchError": "Nie udało się załadować użytkowników. Spróbuj ponownie później.",
    "userManagement.users.emptySelection.view": "Ta grupa nie ma żadnych członków.",
    "userManagement.users.emptySelection.edit": "Nie wybrano użytkowników.",
    "userManagement.users.removeUserFromGroup": "Usuń użytkownika z grupy.",
    "userManagement.users.removeUserFromGroupDisabledTooltip": "Tego użytkownika nie można usunąć z grupy.",
    "userManagement.users.removeUserFromSelection": "Usuń.",
    "userManagement.userGroups.removeUserGroupFromSelection": "Usuń.",
    "userManagement.users.noMatchingItems": "Brak pasującego użytkownika.",
    "userManagement.users.searchPlaceholder": "Wyszukaj użytkowników",
    "userManagement.users.title": "Dodaj członków grupy",
    "userManagement.users.cancelButton": "Anuluj",
    "userManagement.users.addButton": "Dodaj",
    "userManagement.users.addSuccess": "Świetnie! Pomyślnie dodano użytkowników do grupy.",
    "userManagement.users.addFailure": "Dodanie użytkowników do grupy nie powiodło się.",
    "userManagement.users.addToUserGroupsSuccess": "Świetnie! Pomyślnie dodano użytkowników do grup.",
    "userManagement.users.addToUserGroupsFailure": "Nie udało się dodać użytkowników do grup.",
    "userManagement.users.removeSuccess": "Świetnie! Pomyślnie usunięto użytkownika(ów).",
    "userManagement.users.removeFailure": "Usunięcie użytkownika(ów) nie powiodło się.",
    "userManagement.buttons.close": "Zamknij",
    "userManagement.admin.alert": "Administratorzy mają pełny dostęp do wszystkich przestrzeni roboczych, zasobów i działań.",
    "userManagement.adminGroup.alert": "Członkowie mają pełny dostęp do wszystkich przestrzeni roboczych, zasobów i działań.",
    "userManagement.admin.pill": "Administrator",
    "userManagement.createUserGroup.createButton": "Utwórz",
    "userManagement.createUserGroup.cancelButton": "Anuluj",
    "userManagement.createUserGroup.dialogTitle": "Utwórz grupę",
    "userManagement.createUserGroup.inputPlaceholder": "Nazwa",
    "gs.header.account.title": "Konto",
    "visualization.cluster": "Klastrowanie",
    "richText.placeholder": "Użyj Markdown do stylizacji tekstu i odwoływania się do danych:",
    "richText.tooltip": "Możesz użyć składni Markdown do stylizacji opisu:",
    "recurrence.starts": "Zaczyna się od",
    "recurrence.repeats": "Powtórzenia",
    "recurrence.types.hourly": "Godzinowy",
    "recurrence.types.daily": "Codziennie",
    "recurrence.types.weekly": "Co tydzień w {day}",
    "recurrence.types.monthly.last": "Miesięcznie w ostatni {day}",
    "recurrence.types.monthly": "Miesięcznie w {week, select, 1 {pierwszy} 2 {drugi} 3 {trzeci} 4 {czwarty} other {ostatni}} {day}",
    "recurrence.types.cron": "Wyrażenie Cron",
    "gs.header.search": "Szukaj",
    "gs.date.today": "Dzisiaj",
    "gs.date.yesterday": "Wczoraj",
    "recurrence.types.monthly.first": "Miesięcznie pierwszego dnia",
    "recurrence.types.weekly.first": "Co tydzień w pierwszy dzień",
    "recurrence.description.hourly": "Na początku każdej godziny",
    "recurrence.description.daily": "O {hour} każdego dnia",
    "recurrence.description.weekly_first": "O {hour} każdy tydzień zaczyna się",
    "recurrence.description.weekly": "O {hour} w {dayOfWeekName} każdego tygodnia",
    "recurrence.description.monthly_first": "O {hour} każdy miesiąc zaczyna się",
    "recurrence.description.monthly": "O {hour} w {dayOfWeekName} co {weekNumber}. tydzień w miesiącu",
    "semantic-search.error.title": "Nasza usługa wyszukiwania jest tymczasowo niedostępna.",
    "semantic-search.error.text": "Pracujemy nad rozwiązaniem problemu.",
    "semantic-search.no-results": "Nie znaleziono wyników dla “{query}”.",
    "semantic-search.placeholder": "Wyszukaj pulpity nawigacyjne lub wizualizacje…",
    "semantic-search.id": "ID",
    "semantic-search.tags": "Tagi",
    "semantic-search.match": "{score}% zgodności",
    "recurrence.error.too_often": "Błąd: Zbyt wysoka częstotliwość – zmniejsz do maksymalnie 1 na godzinę",
    "recurrence.cron.tooltip": "Użyj formatu Spring cron – sześć pól: sekundy, minuty, godziny, dzień miesiąca, miesiąc, dzień tygodnia <a>Dowiedz się więcej</a>",
    "userManagement.workspace.permission.viewSaveViews": "Widok i Zapisz Widoki",
    "userManagement.workspace.permissionUser.viewSaveViews.tooltip": "Użytkownik może przeglądać pulpity nawigacyjne, które zostały z nim udostępnione, oraz zapisywać stan filtrów pulpitu nawigacyjnego jako widoki osobiste do przyszłego użytku.",
    "userManagement.workspace.permissionGroup.viewSaveViews.tooltip": "Członkowie grupy mogą przeglądać pulpity nawigacyjne, które zostały z nimi udostępnione, oraz zapisywać stan filtrów pulpitów nawigacyjnych jako widoki osobiste do przyszłego użytku.",
    "userManagement.workspace.permission.viewExportSaveViews": "Wyświetl, Eksportuj i Zapisz Widoki",
    "userManagement.workspace.permissionUser.viewExportSaveViews.tooltip": "Obejmuje uprawnienia do przeglądania. Dodatkowo użytkownik może tworzyć, edytować lub usuwać pulpity nawigacyjne i wizualizacje oraz przeglądać LDM i metryki. Może również eksportować pulpity nawigacyjne do plików PDF oraz dane tabelaryczne z wizualizacji do plików XLSX i CSV, a także zapisywać stan filtrów pulpitu nawigacyjnego jako widoki osobiste do przyszłego użytku.",
    "userManagement.workspace.permissionGroup.viewExportSaveViews.tooltip": "Obejmuje uprawnienia do przeglądania. Dodatkowo, członkowie grupy mogą tworzyć, edytować lub usuwać pulpity nawigacyjne i wizualizacje oraz przeglądać LDM i metryki. Mogą również eksportować pulpity nawigacyjne do plików PDF oraz dane tabelaryczne z wizualizacji do plików XLSX i CSV, a także zapisywać stan filtrów pulpitu nawigacyjnego jako widoki osobiste do przyszłego użytku.",
    "userManagement.workspace.edit.title": "Edytuj uprawnienia przestrzeni roboczej",
    "userManagement.workspace.permission.export": "Eksporty",
    "userManagement.workspace.permission.export.tooltip": "Dodaje uprawnienie EXPORT do eksportowania pulpitów nawigacyjnych i wizualizacji w różnych formatach.",
    "userManagement.workspace.permission.exportTabular": "Eksportuj XLSX i CSV",
    "userManagement.workspace.permission.exportTabular.tooltip": "Dodaje uprawnienie EXPORT_TABULAR do eksportowania pulpitów nawigacyjnych i wizualizacji w formatach CSV i XLSX.",
    "userManagement.workspace.permission.exportPdf": "Eksportuj PDF",
    "userManagement.workspace.permission.exportPdf.tooltip": "Dodaje uprawnienie EXPORT_PDF do eksportowania pulpitów nawigacyjnych i wizualizacji jako pliki PDF.",
    "userManagement.workspace.permission.createFilterView": "Zapisane widoki filtrów",
    "userManagement.workspace.permission.createFilterView.tooltip": "Dodaje uprawnienie CREATE_FILTER_VIEW do tworzenia i zapisywania kombinacji filtrów pulpitu nawigacyjnego do szybkiego ponownego użycia.",
    "userManagement.workspace.permission.createAutomation": "Alerty i zaplanowane eksporty",
    "userManagement.workspace.permission.createAutomation.tooltip": "Dodaje uprawnienie CREATE_AUTOMATIONS do tworzenia automatycznych alertów i zaplanowanych eksportów.",
    "userManagement.workspace.granularPermission.noWorkspace": "Nie wybrano obszaru roboczego",
    "userManagement.workspace.granularPermission.hierarchy": "Uwzględnij przestrzenie robocze podrzędne",
    "userManagement.workspace.granularPermission.hierarchy.tooltip": "Zastosowuje uprawnienia do tego obszaru roboczego i wszystkich jego podrzędnych obszarów roboczych.",
    "userManagement.workspace.granularPermission.workspaceAccess.title": "Dostęp do przestrzeni roboczej",
    "userManagement.workspace.granularPermission.additionalAccess.title": "Dodatkowe uprawnienia",
    "userManagement.workspace.granularPermission.help": "Dowiedz się o uprawnieniach w przestrzeni roboczej",
    "userManagement.workspace.granularPermission.view.description": "Umożliwia użytkownikom przeglądanie pulpitów nawigacyjnych, które zostały z nimi udostępnione lub ich grupie użytkowników.",
    "userManagement.workspace.granularPermission.analyze.description": "Pozwala użytkownikom tworzyć, edytować lub usuwać pulpity nawigacyjne i wizualizacje, a także przeglądać Logiczny Model Danych (LDM) i metryki.",
    "userManagement.workspace.granularPermission.manage.description": "Pozwala użytkownikom edytować lub usuwać logiczny model danych i metryki oraz uzyskiwać dostęp do wszystkich pulpitów nawigacyjnych i edytować ich uprawnienia bez ograniczeń.",
    "userManagement.workspace.granularPermission.warning": "<b>Przestroga:</b> Ta czynność spowoduje usunięcie wszystkich zbędnych kombinacji.",
    "userManagement.workspace.permission.and": "i",
    "gs.header.notifications": "Powiadomienia",
    "gs.header.logo.title.accessibility": "{organizationName}logo",
    "gs.header.href.accessibility": "Przejdź do strony głównej",
    "gs.list.acessibility.search.label": "Wyszukaj wartości atrybutów",
    "message.accessibility.dismiss.notification": "Usuń powiadomienie",
    "datePicker.accessibility.label": "Wybierz datę początkową",
    "timePicker.accessibility.label": "Wybierz czas rozpoczęcia",
    "gs.header.accessibility.label": "Globalny nagłówek aplikacji",
    "gs.header.menu.accessibility.label": "Globalna nawigacja",
    "filters.date.accessibility.label.from": "Wybierz datę z",
    "filters.date.accessibility.label.to": "Wybierz datę do",
    "filters.time.accessibility.label.from": "Wybierz czas z",
    "filters.time.accessibility.label.to": "Wybierz czas do",
    "filters.relative.accessibility.label.period.from": "Wybierz okres od",
    "filters.relative.accessibility.label.period.to": "Wybierz okres do",
    "gs.header.help.label": "Linki pomocy",
    "visualizations.pagination.previous": "Poprzednia strona",
    "visualizations.pagination.next": "Następna strona",
    "close": "Zamknij",
    "filters.relative.placeholder": "Wpisz lub wybierz",
    "filters.relative.from.label": "Początek okresu",
    "filters.relative.from.invalid.value": "Błąd: Nieprawidłowy początek okresu – wprowadź prawidłowy okres lub wybierz go z listy.",
    "filters.relative.from.empty.value": "Błąd: Początek okresu jest pusty – wprowadź prawidłowy okres lub wybierz go z listy.",
    "filters.relative.to.label": "Koniec okresu",
    "filters.relative.to.invalid.value": "Błąd: Nieprawidłowy koniec okresu – wprowadź prawidłowy okres lub wybierz go z listy.",
    "filters.relative.to.empty.value": "Błąd: Koniec okresu jest pusty – wprowadź prawidłowy okres lub wybierz go z listy.",
    "richText.no_data": "Brak danych",
    "richText.multiple_data": "Wiele elementów",
    "richText.no_fetch": "Nie można pobrać danych",
    "recurrence.types.inherit": "Domyślna organizacja",
    "recurrence.types.inherit.info": "Użyj domyślnej częstotliwości oceny ustawionej przez Twoją organizację.",
    "recurrence.error.empty": "Błąd: Wymagane pole – wprowadź wyrażenie Spring cron z sześcioma polami: sekundy, minuty, godziny, dzień miesiąca, miesiąc i dzień tygodnia. <a>Dowiedz się więcej</a>",
    "recurrence.error.wrongFormat": "Błąd: Nieprawidłowy format – użyj formatu Spring cron z sześcioma polami: sekundy, minuty, godziny, dzień miesiąca, miesiąc i dzień tygodnia. <a>Dowiedz się więcej</a>",
    "recurrence.datetime.format.help": "Format: {dateFormat}",
    "recurrence.datetime.empty.error": "Błąd: Wymagane pole – wprowadź prawidłową datę, aby kontynuować.",
    "recurrence.datetime.wrong.format.error": "Błąd: Nieprawidłowa data – format musi być {dateFormat}",
    "gs.time": "czas",
    "gs.header.ai": "Otwórz Asystenta AI",
    "visualizations.headline.pagination.next.metricLabel": "Pokaż następną porównawczą metrykę",
    "visualizations.headline.pagination.previous.metricLabel": "Pokaż poprzednią porównawczą metrykę",
    "shareDialog.share.grantee.addLabel": "Dodaj użytkowników lub grupy",
    "shareDialog.share.granular.grantee.permission.label": "Uprawnienie",
    "dialogs.closeLabel": "Zamknij okno dialogowe",
    "dialogs.backButtonLabel": "Powrót do poprzedniego kroku",
    "userManagement.workspace.permission.useAiAssistant": "Asystent AI",
    "userManagement.workspace.permission.useAiAssistant.tooltip": "Dodaje uprawnienie USE_AI_ASSISTANT do dostępu i interakcji z chatbotem AI w celu zadawania pytań analitycznych.",
    "gs.header.workspaceSettings": "Ustawienia przestrzeni roboczej",
    "visualizations.headline.pagination.drill.hint": "Przewijanie dostępne. Naciśnij Enter lub Spację, aby kontynuować.",
    "filters.staticPeriod.dateFrom": "Data początkowa",
    "filters.staticPeriod.timeFrom": "Czas rozpoczęcia",
    "filters.staticPeriod.dateTo": "Data końcowa",
    "filters.staticPeriod.timeTo": "Czas zakończenia",
    "filters.staticPeriod.dateFormatHint": "Użyj formatu daty {format}.",
    "filters.staticPeriod.timeFormatHint": "Użyj formatu czasu GG:MM; maksymalna wartość to 23:59.",
    "filters.staticPeriod.errors.emptyStartDate": "Błąd: Data początkowa jest pusta – wprowadź prawidłową datę, aby kontynuować.",
    "filters.staticPeriod.errors.invalidStartDate": "Błąd: Nieprawidłowa data początkowa – użyj formatu {format}.",
    "filters.staticPeriod.errors.startDateAfterEndDate": "Błąd: Nieprawidłowa data początkowa – ustaw datę przed datą końcową.",
    "filters.staticPeriod.errors.startTimeAfterEndTime": "Błąd: Nieprawidłowy czas rozpoczęcia – ustaw czas przed czasem zakończenia.",
    "filters.staticPeriod.errors.emptyEndDate": "Błąd: Data końcowa jest pusta – wprowadź prawidłową datę, aby kontynuować.",
    "filters.staticPeriod.errors.invalidEndDate": "Błąd: Nieprawidłowa data końcowa – użyj formatu {format}.",
    "filters.staticPeriod.errors.endDateBeforeStartDate": "Błąd: Nieprawidłowa data końcowa – ustaw datę po dacie początkowej.",
    "filters.staticPeriod.errors.endTimeBeforeStartTime": "Błąd: Nieprawidłowy czas zakończenia – ustaw czas po czasie rozpoczęcia.",
    "menu.close": "Zamknij menu",
    "menu.back": "Powrót do menu nadrzędnego",
    "dateFilterDropdown.label": "Wybierz zakres dat",
    "dateFilterDropdown.relativeForm.label": "Granularność",
    "properties.legend.series.item.description": "Użyj do przełączania widoczności",
    "properties.legend.more.button": "Pokaż wszystkie elementy legendy w oknie dialogowym",
    "properties.legend.series.named": "Legenda: {name}",
    "properties.legend.series.unnamed": "Legenda wizualizacji",
    "shareDialog.share.dashboard.title": "Udostępnij pulpit nawigacyjny",
    "shareDialog.share.dashboard.list.title": "Użytkownicy i grupy",
    "shareDialog.share.link.helperText": "Link odzwierciedla bieżące filtry. Dostępny tylko dla użytkowników z dostępem do pulpitu nawigacyjnego.",
    "shareDialog.share.link.title": "Link",
    "shareDialog.share.link.buttonText": "Skopiuj link do pulpitu nawigacyjnego",
    "table.moreActions": "Więcej",
    "table.title.searchPlaceholder": "Szukaj...",
    "table.filter.label": "Filtr",
    "table.filter.searchPlaceholder": "Szukaj...",
    "table.bulkActions.chooseAction": "Wybierz działanie...",
    "table.bulkActions.selectedCount": "{selectedCount} z {totalCount} wybranych",
    "table.emptyState.noMatch": "Nie znaleziono dopasowania",
    "table.emptyState.tryAdjustingFilters": "Sprawdź pisownię lub dostosuj filtry.",
    "filters.thisWeekToDate.title": "Bieżący tydzień (WTD)",
    "filters.thisMonthToDate.title": "Od początku miesiąca (MTD)",
    "filters.thisQuarterToDate.title": "Od początku tego kwartału (QTD)",
    "filters.thisYearToDate.title": "Od początku roku (YTD)",
    "visualizations.headline.comparison.ariaLabel.singleValuePositiveChange": "góra {mainValue}",
    "visualizations.headline.comparison.ariaLabel.singleValueNegativeChange": "w dół {mainValue}",
    "visualizations.headline.comparison.ariaLabel.twoValuesPositiveChange": "w górę {mainValue} (różnica wynosi {secondaryValue})",
    "visualizations.headline.comparison.ariaLabel.twoValuesNegativeChange": "spadek {mainValue} (różnica wynosi {secondaryValue})",
    "visualizations.headline.comparison.ariaLabel.twoValues": "{mainValue} (różnica wynosi {secondaryValue})",
    "filters.staticPeriod.dateTimeFrom": "Data i godzina rozpoczęcia",
    "filters.staticPeriod.dateTimeTo": "Data i godzina zakończenia",
    "filters.floatingRange.tooltip.ariaLabel": "Informacje o Okresie Względnym",
    "recurrence.datetime.timezone.help": "{timezone} Strefa czasowa",
    "messages.accessibility.noMessages": "Brak wiadomości",
    "messages.accessibility.partial.error": "{count, plural, one {# błąd} other {# błędy}}",
    "messages.accessibility.partial.warning": "{count, plural, one {# ostrzeżenie} other {# ostrzeżenia}}",
    "messages.accessibility.partial.success": "{count, plural, one {# sukces} other {# sukcesy}}",
    "messages.accessibility.partial.progress": "{count, plural, one {# postęp} other {# postępy}}",
    "messages.accessibility.label": "{count, plural, one {# wiadomość} other {# wiadomości}}: {partial}",
    "table.bulkActions.selectedCountShort": "{selectedCount} wybrano",
    "visualizations.menu.textWrapping": "Zawijaj tekst",
    "visualizations.menu.textWrapping.header": "Nagłówki",
    "visualizations.menu.textWrapping.cell": "Komórki",
    "visualizations.menu.header.openAriaLabel": "Otwórz menu nagłówka",
    "table.filter.optionAll": "Wszystko",
    "table.filter.optionApply": "Zastosuj",
    "table.filter.optionCancel": "Anuluj",
    "table.bulkActions.selectedFiltersCount": "{selectedCount} wybrano",
    "search.results.none": "Brak pasujących wyników.",
    "search.results.few": "{count, plural, one {# wynik} other {# wyniki}}: {values}",
    "search.results.many": "{count} Wyniki",
    "filters.locked.filter.tooltip": "Ten filtr jest zablokowany",
    "attributesDropdown.alternativeValueTooltip": "Alternatywna wartość z etykiety głównej {label}: {value}",
    "attributesDropdown.filterValues": "Filtruj wartości",
    "attributesDropdown.onlyLabel": "Wybierz tylko {itemTitle}",
    "attributesDropdown.actionsHint.withQuestion": "Filtruj wartości. Użyj klawisza strzałki w prawo, aby przejść do akcji „Wybierz tylko”, a następnie usłysz alternatywną wartość.",
    "attributesDropdown.actionsHint.noQuestion": "Filtruj wartości. Użyj klawisza strzałki w prawo, aby przejść do akcji „Wybierz tylko”",
    "attributesDropdown.noChanges": "Brak zmian do zastosowania",
    "table.filter.error.tooLarge": "<strong>Błąd:</strong> Zbyt duży wybór w filtrach — odznacz niektóre wartości i spróbuj ponownie.",
    "visualizations.menu.sort": "Sortuj",
    "visualizations.menu.sort.ascending": "Rosnąco",
    "visualizations.menu.sort.descending": "Malejąco",
    "dialogs.export.pdf.headline": "Ustawienia eksportu (.pdf)",
    "dialogs.export.pdf.includePageExportInfo": "Uwzględnij informacje o eksporcie strony",
    "dialogs.export.pdf.pageOrientation": "Orientacja",
    "dialogs.export.pdf.pageSize": "Rozmiar strony",
    "dialogs.export.submit": "Eksportuj",
    "gs.list.allAndCount": "Wszystkie ({count})",
    "gs.list.allSearchResultsAndCount": "Wyniki wszystkich wyszukiwań ({count})",
    "attributesDropdown.selectedValues": "Wybrane wartości",
    "attributesDropdown.selected": "wybrano",
    "dialogs.export.pdf.pageSize.option.a3": "A3",
    "dialogs.export.pdf.pageSize.option.a4": "A4",
    "dialogs.export.pdf.pageSize.option.letter": "List",
    "dialogs.export.pdf.pageOrientation.option.portrait": "Portret",
    "dialogs.export.pdf.pageOrientation.option.landscape": "Krajobraz",
    "attributesDropdown.alternativeValueTooltipShort": "({label}: {value})",
    "table.header.ariaLabel": "Nagłówek",
    "table.header.checkbox.ariaLabel": "Wybierz akcję",
    "table.header.menu.ariaLabel": "Akcje",
    "gs.header.mainMenu.ariaLabel": "Główne menu",
    "tabs.all": "Wszystko",
    "tabs.showAllTabs": "Pokaż wszystkie karty",
    "visualizations.totals.dropdown.tooltip.nat.disabled.mvf": "Agregacja podsumowania (Suma) nie jest dostępna podczas filtrowania wizualizacji wg wartości metryki. Aby użyć podsumowania (Suma), usuń wszystkie filtry wartości metryki z paska filtrów.",
    "shareDialog.share.link.helperTextWithTabs": "Link odzwierciedla bieżące filtry na aktywnej karcie. Dostępny tylko dla użytkowników z dostępem do pulpitu nawigacyjnego.",
    "table.bulkActions.selectAll": "Zaznacz wszystko",
    "tabs.actions": "Akcje dla bieżącej karty",
    "visualization.ErrorMessageResultCacheMissing": "Wizualizacja wymaga odświeżenia",
    "visualization.ErrorDescriptionResultCacheMissing": "Dane źródłowe uległy zmianie lub wygasły. Odśwież stronę.",
    "visualizations.table.pagination.of": "z"
}
