{
    "gs.header.help": "Trợ giúp",
    "gs.list.is": "là",
    "gs.color-picker.cancelButton": "Hủy",
    "visualization.ErrorMessageUnauthorized": "Không được phép",
    "gs.filterLabel.none": "Không có",
    "gs.list.cancel": "Hủy",
    "gs.list.limitReached": "Cảnh báo: Bạn đã đạt đến giới hạn {limit} giá trị đã chọn.",
    "gs.list.cannotSelectMoreValues": "Lỗi: Quá nhiều giá trị — bạn có thể thêm tối đa {limit} giá trị.",
    "cancel": "Hủy",
    "close": "Đóng",
    "save": "Lưu",
    "attributeFilter.operator.is": "là",
    "attributeFilter.operator.isNot": "không phải là",
    "attributeFilter.operator.contains": "chứa",
    "attributeFilter.operator.doesNotContain": "không chứa",
    "attributeFilter.operator.startsWith": "bắt đầu bằng",
    "attributeFilter.operator.doesNotStartWith": "không bắt đầu bằng",
    "attributeFilter.operator.endsWith": "kết thúc bằng",
    "attributeFilter.operator.doesNotEndWith": "không kết thúc bằng",
    "attributeFilter.mode.selection": "Lựa chọn",
    "attributeFilter.mode.list": "Danh sách",
    "attributeFilter.mode.text": "Văn bản",
    "attributeFilter.mode.valuesAs": "Giá trị dưới dạng",
    "attributeFilter.text.caseSensitive": "Phân biệt chữ hoa chữ thường",
    "attributeFilter.text.condition": "Điều kiện",
    "attributeFilter.text.arbitrary.placeholder": "Nhập các giá trị ...",
    "attributeFilter.text.match.placeholder": "Nhập giá trị ...",
    "attributeFilter.text.applyButton.tooltip.valuesLimitExceeded": "Bạn không thể có nhiều hơn {maxValues} giá trị.",
    "attributeFilter.text.applyButton.tooltip.emptyValue": "Giá trị trong điều kiện trống.",
    "attributeFilter.text.applyButton.tooltip.noChanges": "Không có thay đổi để áp dụng",
    "attributeFilter.text.validation.valuesLimitReached": "Cảnh báo: Bạn đã đạt đến tối đa {maxValues} giá trị.",
    "attributeFilter.text.validation.valuesLimitExceeded": "Lỗi: Quá nhiều giá trị — bạn có thể thêm tối đa {maxValues} giá trị.",
    "attributeFilter.text.validation.valueCannotBeEmpty": "Lỗi: Giá trị không được để trống.",
    "attributeFilter.text.isNone": "Không có",
    "attributeFilter.text.summary.plain": "{operator} {value}",
    "attributeFilter.text.summary.rich": "{operator} <b>{value}</b>",
    "attributeFilter.text.arbitrary.values": "Giá trị",
    "attributeFilter.text.match.value": "Giá trị",
    "attributeFilter.text.values.tooltip": "Phân tách các giá trị bằng dấu phẩy hoặc xuống dòng.\nSử dụng dấu ngoặc kép nếu nội dung bạn thêm có dấu phẩy.\nĐể lọc các giá trị trống và null, hãy sử dụng {emptyValue}.\nBạn có thể thêm tối đa {maxValues} giá trị.",
    "attributeFilter.text.values.helpIconLabel": "Trợ giúp",
    "attributeFilter.text.values.removeTagAriaLabel": "Loại bỏ {value}",
    "attributeFilter.text.autocomplete.listLabel": "Gợi ý",
    "attributeFilter.details.infoButtonLabel": "Hiển thị chi tiết thuộc tính",
    "attributeFilter.details.label": "Nhãn",
    "attributeFilter.details.elementsMore": "…và {count} nữa",
    "attributeFilter.details.type": "Loại",
    "attributeFilter.details.dataset": "Tập dữ liệu",
    "attributeFilter.details.id": "ID",
    "attributeFilter.details.typeValue": "Thuộc tính",
    "mvf.condition": "Điều kiện",
    "attributesDropdown.noChanges": "Không có thay đổi để áp dụng",
    "attributesDropdown.details.dataset": "Tập dữ liệu",
    "shareDialog.share.granular.grantee.permission.remove": "Xóa",
    "embedInsightDialog.actions.close": "Đóng",
    "stylingEditor.dialog.name": "Tên",
    "attributeHierarchyEditor.button.cancel": "Hủy",
    "attributeHierarchyEditor.remove.attribute": "Xóa",
    "userManagement.userGroups.cancelButton": "Hủy",
    "userManagement.tab.details": "Chi tiết",
    "userManagement.dataSources.permission.remove": "Xóa",
    "userManagement.closeButton": "Đóng",
    "userManagement.workspace.permission.remove": "Xóa",
    "userManagement.groupDetail.id.label": "ID",
    "userManagement.groupDetail.name.label": "Tên",
    "userManagement.userDetail.id.label": "ID",
    "userManagement.userDetail.saveButton": "Lưu",
    "userManagement.userDetail.cancelButton": "Hủy",
    "userManagement.groupDetail.saveButton": "Lưu",
    "userManagement.groupDetail.cancelButton": "Hủy",
    "userManagement.deleteDialog.cancelButton": "Hủy",
    "userManagement.users.cancelButton": "Hủy",
    "userManagement.buttons.close": "Đóng",
    "userManagement.createUserGroup.cancelButton": "Hủy",
    "userManagement.createUserGroup.inputPlaceholder": "Tên",
    "table.filter.optionCancel": "Hủy"
}
