{
    "messages.longSaving": "L'enregistrement prend plus longtemps que prévu, veuillez patienter…",
    "messages.dashboardSaveSuccess": "Votre tableau de bord a été enregistré.",
    "messages.dashboardSaveFailed": "Échec d'enregistrement du tableau de bord, réessayez.",
    "options.menu.save.as": "Enregistrer sous un nouveau nom",
    "options.menu.save.as.tooltip": "Un tableau de bord vide ne peut pas être enregistré.",
    "filterBar.showAll": "Afficher tout",
    "filterBar.showLess": "Montrer moins",
    "options.menu.export.PDF": "Exporter vers PDF",
    "options.menu.schedule.email": "Programmer l'envoi d'e-mails",
    "dialogs.export.cells": "CELLULES",
    "dialogs.export.filters": "CONTEXTE DE LA PERCEPTION",
    "dialogs.export.includeFilters": "Inclure les filtres appliqués",
    "dialogs.export.headline": "Exporter vers XLSX",
    "dialogs.export.mergeHeaders": "Garder les cellules d'attributs fusionnées",
    "dialogs.export.submit": "Exporter",
    "dialogs.schedule.email.submit.success": "Le tableau de bord est programmé pour envoyer des e-mails.",
    "dialogs.schedule.email.submit.error": "Échec de la programmation du tableau de bord. Réessayez plus tard.",
    "drill_modal_picker.drill-down": "Exploration descendante",
    "drill_modal_picker.drill-into": "Explorer",
    "drill_modal_picker.more.details": "Plus de détails",
    "drillModal.backToTop": "Haut de page",
    "filters.allTime.previousPeriod": "période préc.",
    "filters.allTime.lastYear": "année préc.",
    "filters.day.previousPeriod": "préc. {n, plural, one {jour} other {#j}}",
    "filters.week.previousPeriod": "préc. {n, plural, one {semaine} other {#s}}",
    "filters.month.previousPeriod": "préc. {n, plural, one {mois} other {#m}}",
    "filters.quarter.previousPeriod": "préc. {n, plural, one {trimestre} other {#t}}",
    "filters.year.previousPeriod": "préc. {n, plural, one {année} other {#a}}",
    "filters.alertMessage.relativePreset": "dans {calendarIcon} {range}",
    "filters.alertMessage.relativePreset.inPeriod": "de la période de {calendarIcon} {range}",
    "filters.alertMessage.relativePreset.range.day": "{n, plural, =0 {ce jour} =1 {le jour dernier} other {# derniers jours}}",
    "filters.alertMessage.relativePreset.range.week": "{n, plural, =0 {cette semaine} =1 {la semaine dernière} other {# dernières semaines}}",
    "filters.alertMessage.relativePreset.range.month": "{n, plural, =0 {ce mois} =1 {le mois dernier} other {# derniers mois}}",
    "filters.alertMessage.relativePreset.range.quarter": "{n, plural, =0 {ce trimestre} =1 {le trimestre dernier} other {# derniers trimestres}}",
    "filters.alertMessage.relativePreset.range.year": "{n, plural, =0 {cette année} =1 {l'année dernière} other {# dernières années}}",
    "kpi.noData": "Aucune donnée pour les paramètres de filtre actuels. Essayez de modifier les filtres.",
    "kpiPop.change": "modifier",
    "dialogs.schedule.email.attachment.filter": "(avec les filtres configurés actuellement)",
    "dialogs.schedule.email.attachment.label": "Pièce jointe :",
    "dialogs.schedule.email.headline": "Programmer un envoi par e-mail",
    "dialogs.schedule.email.message.label": "Message:",
    "dialogs.schedule.email.repeats.label": "Se répète :",
    "dialogs.schedule.email.repeats.execute.on.dayOfMonth": "le {date} jour",
    "dialogs.schedule.email.repeats.execute.on.dayOfWeek": "le {week, select, 1 {premier} 2 {deuxième} 3 {troisième} 4 {quatrième} other {dernier}} {day}",
    "dialogs.schedule.email.repeats.every": "toutes les",
    "dialogs.schedule.email.repeats.frequencies.day": "{n, plural, one {jour} other {jours}}",
    "dialogs.schedule.email.repeats.frequencies.month": "{n, plural, one {mois} other {mois}}",
    "dialogs.schedule.email.repeats.frequencies.week": "{n, plural, one {semaine} other {semaines}}",
    "dialogs.schedule.email.repeats.types.custom": "Personnalisé",
    "dialogs.schedule.email.repeats.types.daily": "Quotidiennement",
    "dialogs.schedule.email.repeats.types.monthly": "Mensuellement le {week, select, 1 {premier} 2 {deuxième} 3 {troisième} 4 {quatrième} other {dernier}} {day}",
    "dialogs.schedule.email.repeats.types.weekly": "Hebdomadairement le {day}",
    "dialogs.schedule.email.subject.label": "Objet:",
    "dialogs.schedule.email.time.label": "Première occurrence :",
    "dialogs.schedule.email.to.label": "À:",
    "dialogs.schedule.email.message.placeholder": "Bonjour,\n\nvotre e-mail programmé est prêt. Vous pouvez télécharger le tableau de bord dans les pièces jointes.",
    "dialogs.schedule.email.submit": "Planifier",
    "dialogs.save.as.new.title": "Enregistrer en tant que nouveau tableau de bord",
    "dialogs.save.as.new.desc": "Donnez au nouveau tableau de bord un nom descriptif pour le retrouver facilement.",
    "dialogs.save.as.new.default.title": "Copie de {title}",
    "dialogs.save.as.new.alertsAndEmailsMessage": "Les alertes et e-mails planifiés ne seront pas dupliqués.",
    "dialogs.save.as.new.alertsMessage": "Les alertes ne seront pas dupliquées.",
    "dialogs.save.as.new.emailsMessage": "Les e-mails planifiés ne seront pas dupliqués.",
    "create.dashboard": "Créer un tableau de bord",
    "options.menu.schedule.email.recipient.invalid": "Ceci n'est pas une adresse e-mail valide.",
    "options.menu.schedule.email.recipient.warning.existed": "Vous avez déjà ajouté ce destinataire.",
    "options.menu.schedule.email.recipient.warning.belong.workspace": "Cette adresse e-mail n'appartient pas à l'espace de travail. Le destinataire peut recevoir des données sensibles. ",
    "cancel": "Annuler",
    "gs.date.at": "à",
    "kpi.alertBox.title": "Définir une alerte lors de la modification du KPI",
    "kpi.alertBox.example": "Par ex.",
    "kpi.alertBox.unverifiedEmail": "Désolé, vous ne pouvez pas définir une alerte. Assurez-vous que votre e-mail est vérifié. Si cela n'aide pas, demandez à votre administrateur de mettre à jour vos autorisations.",
    "kpi.alertBox.disabledInReadOnly": "Les alertes sont désactivées en mode lecture seule",
    "kpi.error.view": "Impossible d'afficher le KPI. Contactez votre administrateur pour corriger la définition du KPI.",
    "kpiAlertDialog.delete": "Supprimer",
    "kpiAlertDialog.deleting": "Suppression en cours…",
    "kpiAlertDialog.emailMe": "Envoyez-moi un e-mail",
    "kpiAlertDialog.emailMeWhen": "{emailMe} lorsque ce KPI est",
    "kpiAlertDialog.emailInfo": "L'e-mail sera envoyé à {userEmail}",
    "kpiAlertDialog.invalidNumber": "<strong>Ce numéro n'est pas valide.</strong><br />Revérifiez et réessayez.",
    "kpiAlertDialog.filtersDiffer": "KPI est à présent filtré différemment que lors de la configuration de l'alerte.",
    "kpiAlertDialog.filtersApply": "Appliquer les filtres d'alerte au tableau de bord",
    "kpiAlertDialog.savingFailed": "Échec de l'enregistrement de l'alerte. Réessayez.",
    "kpiAlertDialog.deleteingFailed": "Échec de suppression de l'alerte. Réessayez.",
    "kpiAlertDialog.brokenAlert": "Alerte interrompue",
    "kpiAlertDialog.brokenAlertAppeal": "Pour voir la valeur correcte de KPI, mettez à jour les filtres dans cette alerte. Vous pouvez également supprimer l'alerte.",
    "kpiAlertDialog.brokenAlertDefaultDateLabel": "Date",
    "kpiAlertDialog.removedFilters": "Filtres supprimés du tableau de bord",
    "kpiAlertDialog.ignoredFilters": "Filtres ignorés pour ce KPI",
    "kpiAlertDialog.updateTitle": "Mettre à jour",
    "kpiAlertDialog.updateBrokenTitle": "Mettre à jour les filtres",
    "kpiAlertDialog.updatingTitle": "Mise à jour en cours…",
    "kpiAlertDialog.updateBrokenFailed": "Échec de mise à jour des filtres. Réessayez.",
    "kpiAlertDialog.setTitle": "Définir l'alerte",
    "kpiAlertDialog.settingTitle": "Définition en cours…",
    "kpiAlertDialog.threshold.above": "au-dessus de",
    "kpiAlertDialog.threshold.below": "au-dessous de",
    "kpiAlertDialog.withAttributeFilters": "{numFilters} plus {numFilters, select, 1 {filtre} other {filtres}} appliqués",
    "kpiAlertDialog.unsaved.changes.headline": "Quitter le tableau de bord de KPI ?",
    "kpiAlertDialog.unsaved.changes.message": "Certaines modifications ne sont pas publiées et seront perdues.",
    "kpiAlertDialog.unsaved.changes.leave.anyway": "Quitter quand même",
    "kpiAlertDialog.unsaved.changes.stay": "Rester",
    "messages.exportResultError": "Échec de l'exportation des données. Réessayez plus tard.",
    "messages.exportResultRestrictedError": "Vous ne pouvez pas exporter cette perception car elle contient des données à accès restreint.",
    "messages.exportResultStart": "Exportation en cours",
    "messages.exportResultSuccess": "Exportation effectuée",
    "attributeFilterDropdown.searchPlaceholder": "Rechercher…",
    "attributeFilterDropdown.emptyValue": "valeur vide",
    "visualization.dataTooLarge.headline": "Trop de points de données à afficher",
    "visualization.dataTooLarge.text": "Essayez d'appliquer un ou plusieurs filtres à votre tableau de bord.",
    "visualization.execute_protected_report.headline": "Vous n'êtes pas autorisé à consulter ce rapport",
    "visualization.execute_protected_report.text": "Contactez votre administrateur.",
    "visualization.alert_not_supported": "Les alertes ne sont pas prises en charge sur la période de dates statique",
    "visualization.empty.headline": "Aucune donnée pour votre sélection de filtre",
    "visualization.error.headline": "Désolé, nous ne pouvons pas afficher cette perception",
    "visualization.error.text": "Contactez votre administrateur.",
    "options.button.bubble": "Exporter les données de perception",
    "options.menu.export.CSV": "CSV",
    "options.menu.export.XLSX": "XLSX",
    "options.menu.unsupported.error": "La perception ne peut pas être exportée à l'heure actuelle. Essayez d'appliquer d'autres filtres ou d'utiliser d'autres mesures ou attributs.",
    "options.menu.unsupported.loading": "La perception ne peut pas être exportée à l'heure actuelle.",
    "export.defaultTitle": "Perception sans titre",
    "export_unsupported.disabled": "L'exportation n'est pas prise en charge.",
    "widget.options.menu.exportToCSV": "Exporter au format CSV",
    "widget.options.menu.exportToXLSX": "Exporter vers XLSX",
    "dashboard.error.empty.heading": "Ce tableau de bord est vide",
    "dashboard.error.empty.text": "Toutes les perceptions ont été retirées."
}
